gather2gether/VERSION
gather2gether/__init__.py
gather2gether/__main__.py
gather2gether/cli.py
gather2gether/cli_project.py
gather2gether/cli_task.py
gather2gether/cli_user.py
gather2gether/config.py
gather2gether/g2g.py
gather2gether/routes.py
gather2gether/run.py
gather2gether/server.py
gather2gether/db/__init__.py
gather2gether/db/project.py
gather2gether/db/task.py
gather2gether/db/user.py
gather2gether-0.0.4.dist-info/LICENSE
gather2gether-0.0.4.dist-info/METADATA
gather2gether-0.0.4.dist-info/WHEEL
gather2gether-0.0.4.dist-info/entry_points.txt
gather2gether-0.0.4.dist-info/top_level.txt
gather2gether-0.0.4.dist-info/RECORD
