Metadata-Version: 2.1
Name: gather2gether
Version: 0.0.4
Summary: Helps remote people to accomplish tasks together
Home-page: https://github.com/witrdotnet/gather2gether
Author: witrdotnet
Author-email: witr.net@gmail.com
License: UNKNOWN
Platform: UNKNOWN
Classifier: Programming Language :: Python
Classifier: Programming Language :: Python :: 2
Classifier: Programming Language :: Python :: 2.7
Classifier: Programming Language :: Python :: 3
Classifier: Programming Language :: Python :: 3.4
Classifier: Programming Language :: Python :: 3.5
Classifier: Programming Language :: Python :: 3.6
Classifier: Programming Language :: Python :: 3.7
Classifier: Programming Language :: Python :: 3.8
Classifier: License :: OSI Approved :: MIT License
Classifier: Operating System :: OS Independent
Requires-Python: >=2.7
Requires-Dist: Flask
Requires-Dist: Jinja2
Requires-Dist: peewee
Requires-Dist: pymysql
Requires-Dist: configparser
Requires-Dist: tabulate
